jax_cfd/__init__.py
jax_cfd/base/__init__.py
jax_cfd/base/advection.py
jax_cfd/base/advection_test.py
jax_cfd/base/array_utils.py
jax_cfd/base/array_utils_test.py
jax_cfd/base/boundaries.py
jax_cfd/base/boundaries_test.py
jax_cfd/base/diffusion.py
jax_cfd/base/diffusion_test.py
jax_cfd/base/equations.py
jax_cfd/base/equations_test.py
jax_cfd/base/fast_diagonalization.py
jax_cfd/base/fast_diagonalization_test.py
jax_cfd/base/filter_utils.py
jax_cfd/base/finite_differences.py
jax_cfd/base/finite_differences_test.py
jax_cfd/base/forcings.py
jax_cfd/base/forcings_test.py
jax_cfd/base/funcutils.py
jax_cfd/base/funcutils_test.py
jax_cfd/base/grids.py
jax_cfd/base/grids_test.py
jax_cfd/base/initial_conditions.py
jax_cfd/base/initial_conditions_test.py
jax_cfd/base/interpolation.py
jax_cfd/base/interpolation_test.py
jax_cfd/base/pressure.py
jax_cfd/base/pressure_test.py
jax_cfd/base/resize.py
jax_cfd/base/resize_test.py
jax_cfd/base/subgrid_models.py
jax_cfd/base/subgrid_models_test.py
jax_cfd/base/test_util.py
jax_cfd/base/time_stepping.py
jax_cfd/base/time_stepping_test.py
jax_cfd/base/validation_problems.py
jax_cfd/base/validation_test.py
jax_cfd/collocated/__init__.py
jax_cfd/collocated/advection.py
jax_cfd/collocated/advection_test.py
jax_cfd/collocated/diffusion.py
jax_cfd/collocated/diffusion_test.py
jax_cfd/collocated/equations.py
jax_cfd/collocated/equations_test.py
jax_cfd/collocated/initial_conditions.py
jax_cfd/collocated/initial_conditions_test.py
jax_cfd/collocated/pressure.py
jax_cfd/collocated/pressure_test.py
jax_cfd/data/__init__.py
jax_cfd/data/evaluation.py
jax_cfd/data/visualization.py
jax_cfd/data/visualization_test.py
jax_cfd/data/xarray_utils.py
jax_cfd/data/xarray_utils_test.py
jax_cfd/ml/__init__.py
jax_cfd/ml/advections.py
jax_cfd/ml/decoders.py
jax_cfd/ml/diffusions.py
jax_cfd/ml/encoders.py
jax_cfd/ml/equations.py
jax_cfd/ml/equations_test.py
jax_cfd/ml/forcings.py
jax_cfd/ml/interpolations.py
jax_cfd/ml/layers.py
jax_cfd/ml/layers_test.py
jax_cfd-0.2.1.dist-info/LICENSE
jax_cfd-0.2.1.dist-info/METADATA
jax_cfd-0.2.1.dist-info/WHEEL
jax_cfd-0.2.1.dist-info/top_level.txt
jax_cfd-0.2.1.dist-info/RECORD
